facedetection/__init__.py
facedetection/definition.py
facedetection/facedetection.py
facedetection/training.py
facedetection/models/inception_resnet_v1.py
facedetection/models/mtcnn.py
facedetection/models/onet.pt
facedetection/models/pnet.pt
facedetection/models/rnet.pt
facedetection/utils/detect_face.py
facedetection/utils/tensorflow2pytorch.py
facedetection_aeye-0.0.3.dist-info/LICENSE.md
facedetection_aeye-0.0.3.dist-info/METADATA
facedetection_aeye-0.0.3.dist-info/WHEEL
facedetection_aeye-0.0.3.dist-info/top_level.txt
facedetection_aeye-0.0.3.dist-info/RECORD
