Metadata-Version: 2.1
Name: facedetection-aeye
Version: 0.0.3
Summary: Pretrained Pytorch face detection and recognition models for use in the aeye module
Home-page: https://github.com/jjmachan/facedetection-aeye
Author: jjmachan
Author-email: jamesjithin97@gmail.com
License: UNKNOWN
Platform: UNKNOWN
Classifier: Programming Language :: Python :: 3
Classifier: License :: OSI Approved :: MIT License
Classifier: Operating System :: OS Independent
Requires-Dist: numpy
Requires-Dist: requests
